Workbook

Sheet Leia-me
B2: Planilha de Análise de Compras e Estoque
B3: Curva ABC · Giro de Estoque · Mix de Produtos (canibalização) · Estoque > 30 dias · Custo do Estoque Mínimo · Controle de Orçamento
B5: Como usar
B6: 1. Vá até a aba 'Base' e cole sua base completa de estoque a partir da linha 2 (mantendo os mesmos cabeçalhos das colunas A a O).
B7: 2. As colunas de P em diante são calculadas automaticamente — não precisa preencher, só a coluna 'Grupo (opcional)' se quiser mais precisão no mix de produtos.
B8: 3. Ajuste os parâmetros na aba 'Parâmetros' (dias de cobertura alvo por curva, limite de estoque parado, orçamento do mês).
B9: 4. As abas 'Curva ABC', 'Giro de Estoque', 'Estoque Parado', 'Mix e Canibalização' e 'Resumo Executivo' atualizam sozinhas.
B11: Legenda de cores
B12: Azul | C12: Valor de entrada (você preenche/cola)
B13: Preto | C13: Fórmula (não editar)
B14: Amarelo | C14: Parâmetro/premissa chave — revise antes de usar o relatório
B16: Premissas assumidas (ajuste na aba Parâmetros se necessário)
B17: • Estoque mínimo alvo = Venda Diária Média × Dias de Cobertura Alvo da Curva do produto (A=45d, B=30d, C=20d, D=15d, E=10d — política sugerida, edite livremente).
B18: • Venda Diária Média = Venda 90d ÷ 90.
B19: • Giro Anual (x/ano) = 360 ÷ Dias Cobertura (recalculado a partir do campo 'Dias Cobertura' que já vem pronto na sua base).
B20: • 'Estoque parado' = Dias Cobertura acima do limite definido em Parâmetros (padrão: 30 dias).
B21: • Mix/Canibalização: como a base ainda não traz um campo de Grupo/Categoria do Sankhya, a chave de agrupamento usa a 1ª palavra da Descrição por padrão.
B22: Preencha a coluna 'Grupo (opcional)' na aba Base com o grupo real do Sankhya (quando tiver) para um resultado bem mais preciso — a fórmula usa o Grupo automaticamente quando preenchido.
B23: • Custo x Estoque é recalculado como Qtd Estoque × Custo Unit. para garantir consistência, mesmo que sua base já traga essa coluna pronta.
B25: Atenção aos dados de exemplo
B26: Na linha de exemplo (linha 2 da aba Base), os valores de Custo Unit. (R$) e Custo x Estoque (R$) vieram sem separador decimal visível na sua mensagem
B27: (33740 e 134960). Confira se o valor real é R$ 337,40 / R$ 1.349,60 (ou outra casa decimal) antes de colar a base completa, para o formato de moeda não ficar 100x maior que o real.

Sheet Parâmetros
B2: Parâmetros do Modelo
B4: Dias de Cobertura Alvo por Curva (estoque mínimo desejado) | D4: Edite os dias-alvo por curva conforme a política da empresa.
B5: Curva | C5: Dias Alvo
B6: A | C6: 45
B7: B | C7: 30
B8: C | C8: 20
B9: D | C9: 15
B10: E | C10: 10
B13: Limite de Estoque Parado (dias)
B14: Dias acima disso = estoque parado | C14: 30
B17: Orçamento de Compras do Mês
B18: Mês/Ano | C18: 09/2026
B19: Orçamento Total (R$) | C19: 0
B20: Valor Já Comprado no Mês (R$) | C20: 0
B21: % Consumido | C21: =IF(C19=0,"",C20/C19)
B22: Status | C22: =IF(C19=0,"",IF(C21>=1,"TRAVADO (100% do orçamento)",IF(C21>=0.7,"ALERTA (>= 70% do orçamento)","OK")))

Sheet Base
A1: Cod Produto | B1: Descricao | C1: Empresa | D1: Marca | E1: Cod. Fabricante | F1: Curva | G1: Qtd Estoque | H1: Venda 90d | I1: Venda Ano Ant. | J1: Dias Cobertura | K1: Custo Unit. (R$) | L1: Custo x Estoque (R$) | M1: Ultima Compra | N1: Fornecedor | O1: Situacao | P1: Venda Diaria Media | Q1: Dias Cobertura Alvo | R1: Qtd Minima Alvo | S1: Qtd a Comprar (min) | T1: Custo a Comprar (min) (R$) | U1: Estoque > 30 dias? | V1: Chave Mix (auto) | W1: Grupo (opcional) | X1: Chave Mix Final | Y1: Possivel Canibalizacao | Z1: Giro Anual (x/ano) | AA1: Faixa de Giro
A2: 12350 | B2: MOTOR | C2: MMARRA - SERVICE RIBEIRAO PRETO (SP) | D2: SERVICE PECAS | E2: OFICINA MM | F2: E | G2: 4 | H2: 2 | I2: 0 | J2: 180 | K2: 33740 | L2: =IF(A2="","",G2*K2) -> 134960 | M2: 46262 | N2: 512012 | P2: =IF(A2="","",H2/90) -> 0.022222222 | Q2: =IF(A2="","",IFERROR(INDEX(Parâmetros!$C$6:$C$10,MATCH(F2,Parâmetros!$B$6:$B$10,0)),"")) -> 10 | R2: =IF(OR(A2="",P2="",Q2=""),"",P2*Q2) -> 0.22222222 | S2: =IF(R2="","",MAX(0,R2-G2)) -> 0 | T2: =IF(S2="","",S2*K2) -> 0 | U2: =IF(A2="","",IF(J2>Parâmetros!$C$14,"SIM","NAO")) -> SIM | V2: =IF(B2="","",TRIM(LEFT(B2,IFERROR(FIND(" ",B2)-1,LEN(B2))))) -> MOTOR | X2: =IF(A2="","",IF(W2<>"",W2,V2)) -> MOTOR | Y2: =IF(A2="","",IF(COUNTIFS($X$2:$X$2001,X2,$D$2:$D$2001,"<>"&D2,$C$2:$C$2001,C2)>0,"SIM","NAO")) -> NAO | Z2: =IF(A2="","",IF(J2="","",IFERROR(360/J2,""))) -> 2 | AA2: =IF(A2="","",IF(H2=0,"Parado (sem venda 90d)",IF(Z2>12,"Alto (>12x/ano)",IF(Z2>=4,"Medio (4-12x/ano)","Baixo (<4x/ano)")))) -> Baixo (<4x/ano)
L3: =IF(A3="","",G3*K3) | P3: =IF(A3="","",H3/90) | Q3: =IF(A3="","",IFERROR(INDEX(Parâmetros!$C$6:$C$10,MATCH(F3,Parâmetros!$B$6:$B$10,0)),"")) | R3: =IF(OR(A3="",P3="",Q3=""),"",P3*Q3) | S3: =IF(R3="","",MAX(0,R3-G3)) | T3: =IF(S3="","",S3*K3) | U3: =IF(A3="","",IF(J3>Parâmetros!$C$14,"SIM","NAO")) | V3: =IF(B3="","",TRIM(LEFT(B3,IFERROR(FIND(" ",B3)-1,LEN(B3))))) | X3: =IF(A3="","",IF(W3<>"",W3,V3)) | Y3: =IF(A3="","",IF(COUNTIFS($X$2:$X$2001,X3,$D$2:$D$2001,"<>"&D3,$C$2:$C$2001,C3)>0,"SIM","NAO")) | Z3: =IF(A3="","",IF(J3="","",IFERROR(360/J3,""))) | AA3: =IF(A3="","",IF(H3=0,"Parado (sem venda 90d)",IF(Z3>12,"Alto (>12x/ano)",IF(Z3>=4,"Medio (4-12x/ano)","Baixo (<4x/ano)"))))
L4: =IF(A4="","",G4*K4) | P4: =IF(A4="","",H4/90) | Q4: =IF(A4="","",IFERROR(INDEX(Parâmetros!$C$6:$C$10,MATCH(F4,Parâmetros!$B$6:$B$10,0)),"")) | R4: =IF(OR(A4="",P4="",Q4=""),"",P4*Q4) | S4: =IF(R4="","",MAX(0,R4-G4)) | T4: =IF(S4="","",S4*K4) | U4: =IF(A4="","",IF(J4>Parâmetros!$C$14,"SIM","NAO")) | V4: =IF(B4="","",TRIM(LEFT(B4,IFERROR(FIND(" ",B4)-1,LEN(B4))))) | X4: =IF(A4="","",IF(W4<>"",W4,V4)) | Y4: =IF(A4="","",IF(COUNTIFS($X$2:$X$2001,X4,$D$2:$D$2001,"<>"&D4,$C$2:$C$2001,C4)>0,"SIM","NAO")) | Z4: =IF(A4="","",IF(J4="","",IFERROR(360/J4,""))) | AA4: =IF(A4="","",IF(H4=0,"Parado (sem venda 90d)",IF(Z4>12,"Alto (>12x/ano)",IF(Z4>=4,"Medio (4-12x/ano)","Baixo (<4x/ano)"))))
L5: =IF(A5="","",G5*K5) | P5: =IF(A5="","",H5/90) | Q5: =IF(A5="","",IFERROR(INDEX(Parâmetros!$C$6:$C$10,MATCH(F5,Parâmetros!$B$6:$B$10,0)),"")) | R5: =IF(OR(A5="",P5="",Q5=""),"",P5*Q5) | S5: =IF(R5="","",MAX(0,R5-G5)) | T5: =IF(S5="","",S5*K5) | U5: =IF(A5="","",IF(J5>Parâmetros!$C$14,"SIM","NAO")) | V5: =IF(B5="","",TRIM(LEFT(B5,IFERROR(FIND(" ",B5)-1,LEN(B5))))) | X5: =IF(A5="","",IF(W5<>"",W5,V5)) | Y5: =IF(A5="","",IF(COUNTIFS($X$2:$X$2001,X5,$D$2:$D$2001,"<>"&D5,$C$2:$C$2001,C5)>0,"SIM","NAO")) | Z5: =IF(A5="","",IF(J5="","",IFERROR(360/J5,""))) | AA5: =IF(A5="","",IF(H5=0,"Parado (sem venda 90d)",IF(Z5>12,"Alto (>12x/ano)",IF(Z5>=4,"Medio (4-12x/ano)","Baixo (<4x/ano)"))))
L6: =IF(A6="","",G6*K6) | P6: =IF(A6="","",H6/90) | Q6: =IF(A6="","",IFERROR(INDEX(Parâmetros!$C$6:$C$10,MATCH(F6,Parâmetros!$B$6:$B$10,0)),"")) | R6: =IF(OR(A6="",P6="",Q6=""),"",P6*Q6) | S6: =IF(R6="","",MAX(0,R6-G6)) | T6: =IF(S6="","",S6*K6) | U6: =IF(A6="","",IF(J6>Parâmetros!$C$14,"SIM","NAO")) | V6: =IF(B6="","",TRIM(LEFT(B6,IFERROR(FIND(" ",B6)-1,LEN(B6))))) | X6: =IF(A6="","",IF(W6<>"",W6,V6)) | Y6: =IF(A6="","",IF(COUNTIFS($X$2:$X$2001,X6,$D$2:$D$2001,"<>"&D6,$C$2:$C$2001,C6)>0,"SIM","NAO")) | Z6: =IF(A6="","",IF(J6="","",IFERROR(360/J6,""))) | AA6: =IF(A6="","",IF(H6=0,"Parado (sem venda 90d)",IF(Z6>12,"Alto (>12x/ano)",IF(Z6>=4,"Medio (4-12x/ano)","Baixo (<4x/ano)"))))
L7: =IF(A7="","",G7*K7) | P7: =IF(A7="","",H7/90) | Q7: =IF(A7="","",IFERROR(INDEX(Parâmetros!$C$6:$C$10,MATCH(F7,Parâmetros!$B$6:$B$10,0)),"")) | R7: =IF(OR(A7="",P7="",Q7=""),"",P7*Q7) | S7: =IF(R7="","",MAX(0,R7-G7)) | T7: =IF(S7="","",S7*K7) | U7: =IF(A7="","",IF(J7>Parâmetros!$C$14,"SIM","NAO")) | V7: =IF(B7="","",TRIM(LEFT(B7,IFERROR(FIND(" ",B7)-1,LEN(B7))))) | X7: =IF(A7="","",IF(W7<>"",W7,V7)) | Y7: =IF(A7="","",IF(COUNTIFS($X$2:$X$2001,X7,$D$2:$D$2001,"<>"&D7,$C$2:$C$2001,C7)>0,"SIM","NAO")) | Z7: =IF(A7="","",IF(J7="","",IFERROR(360/J7,""))) | AA7: =IF(A7="","",IF(H7=0,"Parado (sem venda 90d)",IF(Z7>12,"Alto (>12x/ano)",IF(Z7>=4,"Medio (4-12x/ano)","Baixo (<4x/ano)"))))
L8: =IF(A8="","",G8*K8) | P8: =IF(A8="","",H8/90) | Q8: =IF(A8="","",IFERROR(INDEX(Parâmetros!$C$6:$C$10,MATCH(F8,Parâmetros!$B$6:$B$10,0)),"")) | R8: =IF(OR(A8="",P8="",Q8=""),"",P8*Q8) | S8: =IF(R8="","",MAX(0,R8-G8)) | T8: =IF(S8="","",S8*K8) | U8: =IF(A8="","",IF(J8>Parâmetros!$C$14,"SIM","NAO")) | V8: =IF(B8="","",TRIM(LEFT(B8,IFERROR(FIND(" ",B8)-1,LEN(B8))))) | X8: =IF(A8="","",IF(W8<>"",W8,V8)) | Y8: =IF(A8="","",IF(COUNTIFS($X$2:$X$2001,X8,$D$2:$D$2001,"<>"&D8,$C$2:$C$2001,C8)>0,"SIM","NAO")) | Z8: =IF(A8="","",IF(J8="","",IFERROR(360/J8,""))) | AA8: =IF(A8="","",IF(H8=0,"Parado (sem venda 90d)",IF(Z8>12,"Alto (>12x/ano)",IF(Z8>=4,"Medio (4-12x/ano)","Baixo (<4x/ano)"))))
L9: =IF(A9="","",G9*K9) | P9: =IF(A9="","",H9/90) | Q9: =IF(A9="","",IFERROR(INDEX(Parâmetros!$C$6:$C$10,MATCH(F9,Parâmetros!$B$6:$B$10,0)),"")) | R9: =IF(OR(A9="",P9="",Q9=""),"",P9*Q9) | S9: =IF(R9="","",MAX(0,R9-G9)) | T9: =IF(S9="","",S9*K9) | U9: =IF(A9="","",IF(J9>Parâmetros!$C$14,"SIM","NAO")) | V9: =IF(B9="","",TRIM(LEFT(B9,IFERROR(FIND(" ",B9)-1,LEN(B9))))) | X9: =IF(A9="","",IF(W9<>"",W9,V9)) | Y9: =IF(A9="","",IF(COUNTIFS($X$2:$X$2001,X9,$D$2:$D$2001,"<>"&D9,$C$2:$C$2001,C9)>0,"SIM","NAO")) | Z9: =IF(A9="","",IF(J9="","",IFERROR(360/J9,""))) | AA9: =IF(A9="","",IF(H9=0,"Parado (sem venda 90d)",IF(Z9>12,"Alto (>12x/ano)",IF(Z9>=4,"Medio (4-12x/ano)","Baixo (<4x/ano)"))))
L10: =IF(A10="","",G10*K10) | P10: =IF(A10="","",H10/90) | Q10: =IF(A10="","",IFERROR(INDEX(Parâmetros!$C$6:$C$10,MATCH(F10,Parâmetros!$B$6:$B$10,0)),"")) | R10: =IF(OR(A10="",P10="",Q10=""),"",P10*Q10) | S10: =IF(R10="","",MAX(0,R10-G10)) | T10: =IF(S10="","",S10*K10) | U10: =IF(A10="","",IF(J10>Parâmetros!$C$14,"SIM","NAO")) | V10: =IF(B10="","",TRIM(LEFT(B10,IFERROR(FIND(" ",B10)-1,LEN(B10))))) | X10: =IF(A10="","",IF(W10<>"",W10,V10)) | Y10: =IF(A10="","",IF(COUNTIFS($X$2:$X$2001,X10,$D$2:$D$2001,"<>"&D10,$C$2:$C$2001,C10)>0,"SIM","NAO")) | Z10: =IF(A10="","",IF(J10="","",IFERROR(360/J10,""))) | AA10: =IF(A10="","",IF(H10=0,"Parado (sem venda 90d)",IF(Z10>12,"Alto (>12x/ano)",IF(Z10>=4,"Medio (4-12x/ano)","Baixo (<4x/ano)"))))
L11: =IF(A11="","",G11*K11) | P11: =IF(A11="","",H11/90) | Q11: =IF(A11="","",IFERROR(INDEX(Parâmetros!$C$6:$C$10,MATCH(F11,Parâmetros!$B$6:$B$10,0)),"")) | R11: =IF(OR(A11="",P11="",Q11=""),"",P11*Q11) | S11: =IF(R11="","",MAX(0,R11-G11)) | T11: =IF(S11="","",S11*K11) | U11: =IF(A11="","",IF(J11>Parâmetros!$C$14,"SIM","NAO")) | V11: =IF(B11="","",TRIM(LEFT(B11,IFERROR(FIND(" ",B11)-1,LEN(B11))))) | X11: =IF(A11="","",IF(W11<>"",W11,V11)) | Y11: =IF(A11="","",IF(COUNTIFS($X$2:$X$2001,X11,$D$2:$D$2001,"<>"&D11,$C$2:$C$2001,C11)>0,"SIM","NAO")) | Z11: =IF(A11="","",IF(J11="","",IFERROR(360/J11,""))) | AA11: =IF(A11="","",IF(H11=0,"Parado (sem venda 90d)",IF(Z11>12,"Alto (>12x/ano)",IF(Z11>=4,"Medio (4-12x/ano)","Baixo (<4x/ano)"))))
L12: =IF(A12="","",G12*K12) | P12: =IF(A12="","",H12/90) | Q12: =IF(A12="","",IFERROR(INDEX(Parâmetros!$C$6:$C$10,MATCH(F12,Parâmetros!$B$6:$B$10,0)),"")) | R12: =IF(OR(A12="",P12="",Q12=""),"",P12*Q12) | S12: =IF(R12="","",MAX(0,R12-G12)) | T12: =IF(S12="","",S12*K12) | U12: =IF(A12="","",IF(J12>Parâmetros!$C$14,"SIM","NAO")) | V12: =IF(B12="","",TRIM(LEFT(B12,IFERROR(FIND(" ",B12)-1,LEN(B12))))) | X12: =IF(A12="","",IF(W12<>"",W12,V12)) | Y12: =IF(A12="","",IF(COUNTIFS($X$2:$X$2001,X12,$D$2:$D$2001,"<>"&D12,$C$2:$C$2001,C12)>0,"SIM","NAO")) | Z12: =IF(A12="","",IF(J12="","",IFERROR(360/J12,""))) | AA12: =IF(A12="","",IF(H12=0,"Parado (sem venda 90d)",IF(Z12>12,"Alto (>12x/ano)",IF(Z12>=4,"Medio (4-12x/ano)","Baixo (<4x/ano)"))))
L13: =IF(A13="","",G13*K13) | P13: =IF(A13="","",H13/90) | Q13: =IF(A13="","",IFERROR(INDEX(Parâmetros!$C$6:$C$10,MATCH(F13,Parâmetros!$B$6:$B$10,0)),"")) | R13: =IF(OR(A13="",P13="",Q13=""),"",P13*Q13) | S13: =IF(R13="","",MAX(0,R13-G13)) | T13: =IF(S13="","",S13*K13) | U13: =IF(A13="","",IF(J13>Parâmetros!$C$14,"SIM","NAO")) | V13: =IF(B13="","",TRIM(LEFT(B13,IFERROR(FIND(" ",B13)-1,LEN(B13))))) | X13: =IF(A13="","",IF(W13<>"",W13,V13)) | Y13: =IF(A13="","",IF(COUNTIFS($X$2:$X$2001,X13,$D$2:$D$2001,"<>"&D13,$C$2:$C$2001,C13)>0,"SIM","NAO")) | Z13: =IF(A13="","",IF(J13="","",IFERROR(360/J13,""))) | AA13: =IF(A13="","",IF(H13=0,"Parado (sem venda 90d)",IF(Z13>12,"Alto (>12x/ano)",IF(Z13>=4,"Medio (4-12x/ano)","Baixo (<4x/ano)"))))
L14: =IF(A14="","",G14*K14) | P14: =IF(A14="","",H14/90) | Q14: =IF(A14="","",IFERROR(INDEX(Parâmetros!$C$6:$C$10,MATCH(F14,Parâmetros!$B$6:$B$10,0)),"")) | R14: =IF(OR(A14="",P14="",Q14=""),"",P14*Q14) | S14: =IF(R14="","",MAX(0,R14-G14)) | T14: =IF(S14="","",S14*K14) | U14: =IF(A14="","",IF(J14>Parâmetros!$C$14,"SIM","NAO")) | V14: =IF(B14="","",TRIM(LEFT(B14,IFERROR(FIND(" ",B14)-1,LEN(B14))))) | X14: =IF(A14="","",IF(W14<>"",W14,V14)) | Y14: =IF(A14="","",IF(COUNTIFS($X$2:$X$2001,X14,$D$2:$D$2001,"<>"&D14,$C$2:$C$2001,C14)>0,"SIM","NAO")) | Z14: =IF(A14="","",IF(J14="","",IFERROR(360/J14,""))) | AA14: =IF(A14="","",IF(H14=0,"Parado (sem venda 90d)",IF(Z14>12,"Alto (>12x/ano)",IF(Z14>=4,"Medio (4-12x/ano)","Baixo (<4x/ano)"))))
... L2001: =IF(A2001="","",G2001*K2001) | P2001: =IF(A2001="","",H2001/90) | Q2001: =IF(A2001="","",IFERROR(INDEX(Parâmetros!$C$6:$C$10,MATCH(F2001,Parâmetros!$B$6:$B$10,0)),"")) | R2001: =IF(OR(A2001="",P2001="",Q2001=""),"",P2001*Q2001) | S2001: =IF(R2001="","",MAX(0,R2001-G2001)) | T2001: =IF(S2001="","",S2001*K2001) | U2001: =IF(A2001="","",IF(J2001>Parâmetros!$C$14,"SIM","NAO")) | V2001: =IF(B2001="","",TRIM(LEFT(B2001,IFERROR(FIND(" ",B2001)-1,LEN(B2001))))) | X2001: =IF(A2001="","",IF(W2001<>"",W2001,V2001)) | Y2001: =IF(A2001="","",IF(COUNTIFS($X$2:$X$2001,X2001,$D$2:$D$2001,"<>"&D2001,$C$2:$C$2001,C2001)>0,"SIM","NAO")) | Z2001: =IF(A2001="","",IF(J2001="","",IFERROR(360/J2001,""))) | AA2001: =IF(A2001="","",IF(H2001=0,"Parado (sem venda 90d)",IF(Z2001>12,"Alto (>12x/ano)",IF(Z2001>=4,"Medio (4-12x/ano)","Baixo (<4x/ano)"))))

Sheet Curva ABC
B2: Relatorio Curva ABC
B4: Curva | C4: Qtd SKUs | D4: Valor em Estoque (R$) | E4: % do Estoque Total | F4: Custo p/ Repor Min. (R$) | G4: Giro Anual Medio | H4: Dias Cobertura Medio
B5: A | C5: =COUNTIFS(Base!$F$2:$F$2001,B5) -> 0 | D5: =SUMIFS(Base!$L$2:$L$2001,Base!$F$2:$F$2001,B5) -> 0 | E5: =IF($D$10=0,"",D5/$D$10) -> 0 | F5: =SUMIFS(Base!$T$2:$T$2001,Base!$F$2:$F$2001,B5) -> 0 | G5: =IFERROR(AVERAGEIFS(Base!$Z$2:$Z$2001,Base!$F$2:$F$2001,B5),"") | H5: =IFERROR(AVERAGEIFS(Base!$J$2:$J$2001,Base!$F$2:$F$2001,B5),"")
B6: B | C6: =COUNTIFS(Base!$F$2:$F$2001,B6) -> 0 | D6: =SUMIFS(Base!$L$2:$L$2001,Base!$F$2:$F$2001,B6) -> 0 | E6: =IF($D$10=0,"",D6/$D$10) -> 0 | F6: =SUMIFS(Base!$T$2:$T$2001,Base!$F$2:$F$2001,B6) -> 0 | G6: =IFERROR(AVERAGEIFS(Base!$Z$2:$Z$2001,Base!$F$2:$F$2001,B6),"") | H6: =IFERROR(AVERAGEIFS(Base!$J$2:$J$2001,Base!$F$2:$F$2001,B6),"")
B7: C | C7: =COUNTIFS(Base!$F$2:$F$2001,B7) -> 0 | D7: =SUMIFS(Base!$L$2:$L$2001,Base!$F$2:$F$2001,B7) -> 0 | E7: =IF($D$10=0,"",D7/$D$10) -> 0 | F7: =SUMIFS(Base!$T$2:$T$2001,Base!$F$2:$F$2001,B7) -> 0 | G7: =IFERROR(AVERAGEIFS(Base!$Z$2:$Z$2001,Base!$F$2:$F$2001,B7),"") | H7: =IFERROR(AVERAGEIFS(Base!$J$2:$J$2001,Base!$F$2:$F$2001,B7),"")
B8: D | C8: =COUNTIFS(Base!$F$2:$F$2001,B8) -> 0 | D8: =SUMIFS(Base!$L$2:$L$2001,Base!$F$2:$F$2001,B8) -> 0 | E8: =IF($D$10=0,"",D8/$D$10) -> 0 | F8: =SUMIFS(Base!$T$2:$T$2001,Base!$F$2:$F$2001,B8) -> 0 | G8: =IFERROR(AVERAGEIFS(Base!$Z$2:$Z$2001,Base!$F$2:$F$2001,B8),"") | H8: =IFERROR(AVERAGEIFS(Base!$J$2:$J$2001,Base!$F$2:$F$2001,B8),"")
B9: E | C9: =COUNTIFS(Base!$F$2:$F$2001,B9) -> 1 | D9: =SUMIFS(Base!$L$2:$L$2001,Base!$F$2:$F$2001,B9) -> 134960 | E9: =IF($D$10=0,"",D9/$D$10) -> 1 | F9: =SUMIFS(Base!$T$2:$T$2001,Base!$F$2:$F$2001,B9) -> 0 | G9: =IFERROR(AVERAGEIFS(Base!$Z$2:$Z$2001,Base!$F$2:$F$2001,B9),"") -> 2 | H9: =IFERROR(AVERAGEIFS(Base!$J$2:$J$2001,Base!$F$2:$F$2001,B9),"") -> 180
B10: Total | C10: =SUM(C5:C9) -> 1 | D10: =SUM(D5:D9) -> 134960 | E10: =IF($D$10=0,"",D10/$D$10) -> 1 | F10: =SUM(F5:F9) -> 0
B12: Curva ja vem classificada na sua base (coluna Curva). Esta aba consolida valor de estoque, custo para repor o minimo e giro por curva.

Sheet Giro de Estoque
B2: Analise de Giro de Estoque
B4: Faixa de Giro | C4: Qtd SKUs | D4: Valor em Estoque (R$) | E4: % do Estoque Total
B5: Alto (>12x/ano) | C5: =COUNTIFS(Base!$AA$2:$AA$2001,B5) -> 0 | D5: =SUMIFS(Base!$L$2:$L$2001,Base!$AA$2:$AA$2001,B5) -> 0 | E5: =IF($C$9=0,"",D5/$D$9) -> 0
B6: Medio (4-12x/ano) | C6: =COUNTIFS(Base!$AA$2:$AA$2001,B6) -> 0 | D6: =SUMIFS(Base!$L$2:$L$2001,Base!$AA$2:$AA$2001,B6) -> 0 | E6: =IF($C$9=0,"",D6/$D$9) -> 0
B7: Baixo (<4x/ano) | C7: =COUNTIFS(Base!$AA$2:$AA$2001,B7) -> 1 | D7: =SUMIFS(Base!$L$2:$L$2001,Base!$AA$2:$AA$2001,B7) -> 134960 | E7: =IF($C$9=0,"",D7/$D$9) -> 1
B8: Parado (sem venda 90d) | C8: =COUNTIFS(Base!$AA$2:$AA$2001,B8) -> 0 | D8: =SUMIFS(Base!$L$2:$L$2001,Base!$AA$2:$AA$2001,B8) -> 0 | E8: =IF($C$9=0,"",D8/$D$9) -> 0
B9: Total | C9: =SUM(C5:C8) -> 1 | D9: =SUM(D5:D8) -> 134960
B12: Giro Anual Medio da Rede (x/ano) | C12: =IFERROR(AVERAGE(Base!$Z$2:$Z$2001),"") -> 2
B14: Giro Anual = 360 / Dias Cobertura (a partir do campo Dias Cobertura da sua base). Parado = produtos sem nenhuma venda nos ultimos 90 dias.

Sheet Estoque Parado
B2: Estoque Acima do Limite de Cobertura (padrao: 30 dias)
B4: Valor Total em Estoque (R$) | C4: =SUM(Base!$L$2:$L$2001) -> 134960
B5: Valor em Estoque > limite (R$) | C5: =SUMIFS(Base!$L$2:$L$2001,Base!$U$2:$U$2001,"SIM") -> 134960
B6: % do Estoque Total Parado | C6: =IF(C4=0,"",C5/C4) -> 1 | D6: Limite definido em Parametros (padrao 30 dias)
B7: Qtd de SKUs Parados | C7: =COUNTIF(Base!$U$2:$U$2001,"SIM") -> 1
B10: Detalhamento por severidade
B11: Faixa de Dias em Estoque | C11: Qtd SKUs | D11: Valor em Estoque (R$) | E11: % do Estoque Total
B12: >30 e <=60 dias | C12: =COUNTIFS(Base!$J$2:$J$2001,">30",Base!$J$2:$J$2001,"<=60") -> 0 | D12: =SUMIFS(Base!$L$2:$L$2001,Base!$J$2:$J$2001,">30",Base!$J$2:$J$2001,"<=60") -> 0 | E12: =IF($C$4=0,"",D12/$C$4) -> 0
B13: >60 e <=90 dias | C13: =COUNTIFS(Base!$J$2:$J$2001,">60",Base!$J$2:$J$2001,"<=90") -> 0 | D13: =SUMIFS(Base!$L$2:$L$2001,Base!$J$2:$J$2001,">60",Base!$J$2:$J$2001,"<=90") -> 0 | E13: =IF($C$4=0,"",D13/$C$4) -> 0
B14: >90 e <=180 dias | C14: =COUNTIFS(Base!$J$2:$J$2001,">90",Base!$J$2:$J$2001,"<=180") -> 1 | D14: =SUMIFS(Base!$L$2:$L$2001,Base!$J$2:$J$2001,">90",Base!$J$2:$J$2001,"<=180") -> 134960 | E14: =IF($C$4=0,"",D14/$C$4) -> 1
B15: >180 dias | C15: =COUNTIF(Base!$J$2:$J$2001,">180") -> 0 | D15: =SUMIF(Base!$J$2:$J$2001,">180",Base!$L$2:$L$2001) -> 0 | E15: =IF($C$4=0,"",D15/$C$4) -> 0

Sheet Mix e Canibalizacao
B2: Mix de Produtos - Possivel Canibalizacao
B4: Qtd de SKUs sinalizados (mesmo grupo, outra marca, mesma empresa) | C4: =COUNTIF(Base!$Y$2:$Y$2001,"SIM") -> 0
B5: Valor em Estoque nesses SKUs (R$) | C5: =SUMIFS(Base!$L$2:$L$2001,Base!$Y$2:$Y$2001,"SIM") -> 0
B6: % do Estoque Total em risco de canibalizacao | C6: =IF(SUM(Base!$L$2:$L$2001)=0,"",C5/SUM(Base!$L$2:$L$2001)) -> 0
B9: Como funciona
B10: Um SKU e sinalizado "SIM" quando existe, na mesma empresa/filial, outro produto com a mesma
B11: "Chave Mix" (coluna X da aba Base) mas de marca diferente - ou seja, dois ou mais fornecedores
B12: competindo pelo mesmo tipo de produto/aplicacao (possiveis itens canibais).
B14: A Chave Mix usa por padrao a 1a palavra da Descricao. Ela fica bem mais precisa se voce
B15: preencher a coluna 'Grupo (opcional)' na aba Base com o Grupo/Categoria real do Sankhya
B16: (a formula passa a usar o Grupo automaticamente assim que ele for preenchido).
B18: Para ver os grupos com canibalizacao um a um (ex: quais marcas competem em qual grupo,
B19: com valor de estoque parado de cada lado), monte uma Tabela Dinamica a partir da aba Base:
B20: Inserir > Tabela Dinamica > Linhas: Chave Mix Final (X) e Marca (D) > Valores: Custo x Estoque (L),
B21: soma; e Contagem de Cod Produto (A). Assim voce ve, grupo a grupo, quanto capital esta parado
B22: competindo dentro do proprio mix.

Sheet Custo Estoque Minimo
B2: Quanto custaria comprar tudo o que falta para o Estoque Minimo
B4: Custo Total para Repor o Estoque Minimo (R$) | C4: =SUM(Base!$T$2:$T$2001) -> 0 | D4: Soma de (Qtd Minima Alvo - Qtd Estoque atual) x Custo Unit., so onde falta estoque
B5: Qtd de SKUs abaixo do minimo | C5: =COUNTIF(Base!$S$2:$S$2001,">0") -> 0
B6: Valor Total em Estoque Atual (R$) | C6: =SUM(Base!$L$2:$L$2001) -> 134960
B7: Custo Repor Min. vs Orcamento do Mes | C7: =IF(Parâmetros!$C$19=0,"",C4/Parâmetros!$C$19) | D7: Compara o valor necessario para repor o minimo com o orcamento de compras do mes (aba Parametros)
B10: Como e calculado
B11: Estoque Minimo Alvo (por produto) = Venda Diaria Media x Dias de Cobertura Alvo da Curva
B12: (dias-alvo por curva editaveis na aba Parametros).
B14: Se a Qtd Estoque atual for menor que o Estoque Minimo Alvo, a diferenca (coluna S da aba Base)
B15: e multiplicada pelo Custo Unit. do produto (coluna T da aba Base) e somada aqui.
B17: Produtos que ja estao no minimo ou acima nao entram na conta (nao gera compra negativa).

Sheet Resumo Executivo
B2: Resumo Executivo - Analise Preliminar de Compras e Estoque
B4: Valor Total em Estoque (R$) | C4: ='Custo Estoque Minimo'!C6 -> 134960
B5: Custo p/ Repor o Estoque Minimo (R$) | C5: ='Custo Estoque Minimo'!C4 -> 0 | D5: Quanto falta investir para chegar no minimo ideal
B6: Custo Repor Minimo vs Orcamento do Mes | C6: ='Custo Estoque Minimo'!C7
B8: % do Estoque Parado (> limite de dias) | C8: ='Estoque Parado'!C6 -> 1 | D8: Estoque 'ruim' que nao gira - capital preso
B9: Valor em Estoque Parado (R$) | C9: ='Estoque Parado'!C5 -> 134960
B10: Giro Anual Medio da Rede (x/ano) | C10: ='Giro de Estoque'!C12 -> 2
B12: Valor em Risco de Canibalizacao de Mix (R$) | C12: ='Mix e Canibalizacao'!C5 -> 0
B13: % do Estoque em Risco de Canibalizacao | C13: ='Mix e Canibalizacao'!C6 -> 0
B15: Orcamento de Compras do Mes (R$) | C15: =Parâmetros!C19 -> 0
B16: Valor Ja Comprado no Mes (R$) | C16: =Parâmetros!C20 -> 0
B17: % do Orcamento Consumido | C17: =Parâmetros!C21
B18: Status do Orcamento | C18: =Parâmetros!C22
B21: Leitura sugerida para a reuniao
B22: 1. Custo p/ Repor o Minimo alto + Orcamento apertado = priorize repor primeiro os SKUs
B23: Curva A/B (aba Curva ABC) antes de qualquer compra fora do mix habitual.
B24: 2. % Estoque Parado alto = boa parte dos R$ presos no estoque nao volta como caixa tao cedo;
B25: avalie liquidacao/devolucao a fornecedor para as faixas >90 e >180 dias (aba Estoque Parado).
B26: 3. Valor em Risco de Canibalizacao = capital duplicado comprando o mesmo tipo de produto de
B27: marcas concorrentes; vale revisar politica de compras por grupo (aba Mix e Canibalizacao).
B28: 4. Compras fora do mix habitual (produtos que a empresa normalmente nao comercializa) nao
B29: aparecem automaticamente aqui - filtre a coluna Situacao/Fornecedor na aba Base para mapear.
